Metadata-Version: 2.1
Name: easy-sqla-orm
Version: 0.1.0
Summary: A wrapper on top of sqlalchemy that allow to make django orm style query
License: GNU GPLv3
Author: Soumaila Kouriba
Author-email: admin@softmali.com
Requires-Python: >=3.7,<4.0
Classifier: License :: Other/Proprietary License
Classifier: Programming Language :: Python :: 3
Classifier: Programming Language :: Python :: 3.7
Classifier: Programming Language :: Python :: 3.8
Classifier: Programming Language :: Python :: 3.9
Classifier: Programming Language :: Python :: 3.10
Classifier: Programming Language :: Python :: 3.11
Requires-Dist: PyYAML (>=6.0,<7.0)
Requires-Dist: SQLAlchemy (>=1.4.41,<2.0.0)
Requires-Dist: cfgv (>=3.3.1,<4.0.0)
Requires-Dist: distlib (>=0.3.6,<0.4.0)
Requires-Dist: filelock (>=3.8.0,<4.0.0)
Requires-Dist: greenlet (>=1.1.3,<2.0.0)
Requires-Dist: identify (>=2.5.5,<3.0.0)
Requires-Dist: nodeenv (>=1.7.0,<2.0.0)
Requires-Dist: platformdirs (>=2.5.2,<3.0.0)
Requires-Dist: psycopg2-binary (>=2.9.6,<3.0.0)
Requires-Dist: pydantic (>=1.10.2,<2.0.0)
Requires-Dist: toml (>=0.10.2,<0.11.0)
Requires-Dist: typing-extensions (>=4.3.0,<5.0.0)
